kaira/__init__.py
kaira/version.py
kaira/benchmarks/__init__.py
kaira/benchmarks/base.py
kaira/benchmarks/config.py
kaira/benchmarks/ecc_benchmark.py
kaira/benchmarks/ecc_configs.py
kaira/benchmarks/ldpc_benchmark.py
kaira/benchmarks/metrics.py
kaira/benchmarks/registry.py
kaira/benchmarks/results_manager.py
kaira/benchmarks/runners.py
kaira/benchmarks/standard.py
kaira/benchmarks/visualization.py
kaira/channels/__init__.py
kaira/channels/analog.py
kaira/channels/base.py
kaira/channels/digital.py
kaira/channels/identity.py
kaira/channels/lambda_channel.py
kaira/channels/registry.py
kaira/channels/uplink_mac.py
kaira/constraints/__init__.py
kaira/constraints/antenna.py
kaira/constraints/base.py
kaira/constraints/composite.py
kaira/constraints/identity.py
kaira/constraints/lambda_constraint.py
kaira/constraints/power.py
kaira/constraints/registry.py
kaira/constraints/signal.py
kaira/constraints/utils.py
kaira/data/__init__.py
kaira/data/correlation.py
kaira/data/generation.py
kaira/data/sample_data.py
kaira/losses/__init__.py
kaira/losses/adversarial.py
kaira/losses/audio.py
kaira/losses/base.py
kaira/losses/composite.py
kaira/losses/image.py
kaira/losses/multimodal.py
kaira/losses/registry.py
kaira/losses/text.py
kaira/metrics/__init__.py
kaira/metrics/base.py
kaira/metrics/composite.py
kaira/metrics/registry.py
kaira/metrics/utils.py
kaira/metrics/image/__init__.py
kaira/metrics/image/lpips.py
kaira/metrics/image/psnr.py
kaira/metrics/image/ssim.py
kaira/metrics/signal/__init__.py
kaira/metrics/signal/ber.py
kaira/metrics/signal/bler.py
kaira/metrics/signal/evm.py
kaira/metrics/signal/snr.py
kaira/models/__init__.py
kaira/models/base.py
kaira/models/channel_code.py
kaira/models/deepjscc.py
kaira/models/feedback_channel.py
kaira/models/multiple_access_channel.py
kaira/models/registry.py
kaira/models/wyner_ziv.py
kaira/models/binary/__init__.py
kaira/models/binary/soft_bit_thresholding.py
kaira/models/components/__init__.py
kaira/models/components/afmodule.py
pykaira-0.2.1.dist-info/licenses/LICENSE
pykaira-0.2.1.dist-info/METADATA
pykaira-0.2.1.dist-info/WHEEL
pykaira-0.2.1.dist-info/entry_points.txt
pykaira-0.2.1.dist-info/top_level.txt
pykaira-0.2.1.dist-info/RECORD
