Metadata-Version: 2.4
Name: pykaira
Version: 0.2.1
Summary: A PyTorch-based toolkit for simulating communication systems.
Home-page: https://github.com/ipc-lab/kaira
Author: Selim Firat Yilmaz
Author-email: yilmazselimfirat@gmail.com
License: MIT
Project-URL: Documentation, https://kaira.readthedocs.io
Project-URL: Source, https://github.com/ipc-lab/kaira
Project-URL: Tracker, https://github.com/ipc-lab/kaira/issues
Project-URL: Changelog, https://github.com/ipc-lab/kaira/blob/main/CHANGELOG.md
Keywords: wireless communication,communications,simulation,toolbox,channel modeling,signal processing,pytorch,deep learning,machine learning
Classifier: Development Status :: 3 - Alpha
Classifier: Intended Audience :: Education
Classifier: Intended Audience :: Developers
Classifier: Intended Audience :: Science/Research
Classifier: License :: OSI Approved :: MIT License
Classifier: Operating System :: Unix
Classifier: Operating System :: MacOS
Classifier: Operating System :: Microsoft :: Windows
Classifier: Topic :: Scientific/Engineering :: Artificial Intelligence
Classifier: Topic :: Communications
Classifier: Topic :: Software Development :: Libraries
Classifier: Programming Language :: Python :: 3 :: Only
Classifier: Programming Language :: Python :: 3.10
Classifier: Programming Language :: Python :: 3.11
Classifier: Programming Language :: Python :: 3.12
Classifier: Programming Language :: Python :: 3.13
Requires-Python: >=3.10
License-File: LICENSE
Requires-Dist: torch>=1.8.0
Requires-Dist: torchmetrics
Requires-Dist: joblib
Requires-Dist: torchvision
Requires-Dist: compressai
Requires-Dist: torchaudio
Requires-Dist: seaborn
Requires-Dist: numpy
Dynamic: author
Dynamic: author-email
Dynamic: classifier
Dynamic: description
Dynamic: description-content-type
Dynamic: home-page
Dynamic: keywords
Dynamic: license
Dynamic: license-file
Dynamic: project-url
Dynamic: requires-dist
Dynamic: requires-python
Dynamic: summary
